halophot/__init__.py
halophot/halo_objectives.py
halophot/halo_tools.py
halophot/kephalophot.py
halophot-0.7.6.1.data/scripts/halo
halophot-0.7.6.1.dist-info/METADATA
halophot-0.7.6.1.dist-info/WHEEL
halophot-0.7.6.1.dist-info/top_level.txt
halophot-0.7.6.1.dist-info/RECORD
